rai_checklist_cli/__init__.py
rai_checklist_cli/__main__.py
rai_checklist_cli/checklist_generator.py
rai_checklist_cli/cli.py
rai_checklist_cli/colab_utils.py
rai_checklist_cli/config.py
rai_checklist_cli/jupyter_template_manager.py
rai_checklist_cli/template_manager.py
rai_checklist_cli/template_utils.py
rai_checklist_cli/templates.yaml
rai_checklist_cli/validate_checklist.py
tests/__init__.py
tests/test_cli.py
tests/test_integration.py
rai_checklist_cli-0.7.4.dist-info/LICENSE
rai_checklist_cli-0.7.4.dist-info/METADATA
rai_checklist_cli-0.7.4.dist-info/WHEEL
rai_checklist_cli-0.7.4.dist-info/entry_points.txt
rai_checklist_cli-0.7.4.dist-info/top_level.txt
rai_checklist_cli-0.7.4.dist-info/RECORD
