Metadata-Version: 2.1
Name: rai-checklist-cli
Version: 0.7.4
Summary: A CLI tool to generate responsible AI checklists for machine learning projects.
Home-page: https://github.com/ByteanAtomResearch/rai-checklist-cli
Author: Noble Ackerson
Author-email: noblel@byteanatom.com
License: UNKNOWN
Platform: UNKNOWN
Classifier: Programming Language :: Python :: 3
Classifier: License :: OSI Approved :: MIT License
Classifier: Operating System :: OS Independent
License-File: LICENSE
Requires-Dist: pyyaml
Requires-Dist: tqdm
Requires-Dist: ipywidgets
Requires-Dist: google-generativeai
